easee/__init__.py
easee/__main__.py
easee/charger.py
easee/easee.py
easee/exceptions.py
easee/site.py
easee/utils.py
easee-0.7.20.dist-info/LICENSE
easee-0.7.20.dist-info/METADATA
easee-0.7.20.dist-info/WHEEL
easee-0.7.20.dist-info/entry_points.txt
easee-0.7.20.dist-info/top_level.txt
easee-0.7.20.dist-info/RECORD
