Metadata-Version: 2.1
Name: easee
Version: 0.7.20
Summary: Easee EV charger APi library
Home-page: https://github.com/fondberg/easee
Author: Niklas Fondberg
Author-email: niklas.fondberg@gmail.com
License: MIT
Platform: UNKNOWN
Classifier: License :: OSI Approved :: MIT License
Classifier: Programming Language :: Python
Classifier: Programming Language :: Python :: 3
Requires-Dist: aiohttp
